ads_placement_guardian/__init__.py
ads_placement_guardian/server.py
ads_placement_guardian/img/gtechlogo.png
ads_placement_guardian/static/favicon.ico
ads_placement_guardian/static/index.html
ads_placement_guardian/static/main.1880b8165c963cad.js
ads_placement_guardian/static/polyfills.1a4a779d95e3f377.js
ads_placement_guardian/static/runtime.1eef65174679b3b8.js
ads_placement_guardian/static/styles.9b68e15c04d9fa61.css
ads_placement_guardian-0.1.8.dist-info/METADATA
ads_placement_guardian-0.1.8.dist-info/WHEEL
ads_placement_guardian-0.1.8.dist-info/top_level.txt
ads_placement_guardian-0.1.8.dist-info/RECORD
